lab/source/Lab2_Task4.v
module Lab2_Task4(
    input [1:0] mode,
    input signed [7:0] current_temperature,
    input signed [7:0] target_temperature,
    output reg [1:0] air_condition,
    output reg [1:0] heater
  );

  reg signed [7:0] diff_temperature;
  reg [7:0] abs_diff_temperature;

  always @(*) begin
    diff_temperature = current_temperature - target_temperature;
    case (mode)
      0: begin
        air_condition = 0;
        heater = 0;
      end
      1: begin
        air_condition = 0;
        heater = (diff_temperature <= - 5) ? 2 : 1;
      end
      2: begin
        heater = 0;
        air_condition = (diff_temperature >= 5) ? 2 : 1;
      end
      3: begin
        abs_diff_temperature = diff_temperature < 0 ? ~diff_temperature + 1 : diff_temperature;
        if (abs_diff_temperature < 1) begin
          air_condition = 0;
          heater = 0;
        end
        else if (diff_temperature >= 1) begin
          heater = 0;
          air_condition = (diff_temperature >= 5) ? 2 : 1;
        end
        else if (diff_temperature <= -1) begin
          air_condition = 0;
          heater = (diff_temperature <= - 5) ? 2 : 1;
        end
        else begin
          air_condition = 0;
          heater = 0;
        end
      end
      default: begin
        air_condition = 0;
        heater = 0;
      end
    endcase
  end

endmodule

lab/source/tb_Lab2_Task4.v
`timescale 1ns/1ps

module tb_Lab2_Task4(

  );

  reg [1:0] mode;
  reg signed [7:0] current_temperature;
  reg signed [7:0] target_temperature;
  reg [1:0] air_condition;
  reg [1:0] heater;

  Lab2_Task4 uut (
               .mode                	(mode                 ),
               .current_temperature 	(current_temperature  ),
               .target_temperature  	(target_temperature   ),
               .air_condition       	(air_condition        ),
               .heater              	(heater               )
             );

  initial begin
    // 1. All off mode
    mode = 2'd0;
    current_temperature = 8'sd25;
    target_temperature  = 8'sd20;
    #100;

    // 2. Heating: high power boundary
    mode = 2'd1;
    current_temperature = 8'sd15;
    target_temperature  = 8'sd20;
    #100;

    // 3. Heating: low power boundary
    mode = 2'd1;
    current_temperature = 8'sd16;
    target_temperature  = 8'sd20;
    #100;

    // 4. Heating: equal temperature
    mode = 2'd1;
    current_temperature = 8'sd20;
    target_temperature  = 8'sd20;
    #100;

    // 5. Heating: current > target
    mode = 2'd1;
    current_temperature = 8'sd25;
    target_temperature  = 8'sd20;
    #100;

    // 6. Cooling: high power boundary
    mode = 2'd2;
    current_temperature = 8'sd25;
    target_temperature  = 8'sd20;
    #100;

    // 7. Cooling: low power boundary
    mode = 2'd2;
    current_temperature = 8'sd24;
    target_temperature  = 8'sd20;
    #100;

    // 8. Cooling: equal temperature
    mode = 2'd2;
    current_temperature = 8'sd20;
    target_temperature  = 8'sd20;
    #100;

    // 9. Cooling: current < target
    mode = 2'd2;
    current_temperature = 8'sd15;
    target_temperature  = 8'sd20;
    #100;

    // 10. Automatic: equal
    mode = 2'd3;
    current_temperature = 8'sd20;
    target_temperature  = 8'sd20;
    #100;

    // 11. Automatic: +1, AC low
    current_temperature = 8'sd21;
    target_temperature  = 8'sd20;
    #100;

    // 12. Automatic: +4, AC low
    current_temperature = 8'sd24;
    target_temperature  = 8'sd20;
    #100;

    // 13. Automatic: +5, AC high
    current_temperature = 8'sd25;
    target_temperature  = 8'sd20;
    #100;

    // 14. Automatic: -1, heater low
    current_temperature = 8'sd19;
    target_temperature  = 8'sd20;
    #100;

    // 15. Automatic: -4, heater low
    current_temperature = 8'sd16;
    target_temperature  = 8'sd20;
    #100;

    // 16. Automatic: -5, heater high
    current_temperature = 8'sd15;
    target_temperature  = 8'sd20;
    #100;

    // 17. Negative temperature: heater high
    mode = 2'd3;
    current_temperature = -8'sd15;
    target_temperature  = -8'sd10;
    #100;

    // 18. Negative temperature: AC high
    current_temperature = -8'sd5;
    target_temperature  = -8'sd10;
    #100;

    $finish;
  end

  initial begin
    $dumpfile("tb_Lab2_Task4.vcd");
    $dumpvars;
  end

endmodule

tb_Lab2_Task4.vcd
$date
	Fri Oct  9 11:45:39 2026
$end
$version
	Icarus Verilog
$end
$timescale
	1ps
$end
$scope module tb_Lab2_Task4 $end
$var wire 2 ! heater [1:0] $end
$var wire 2 " air_condition [1:0] $end
$var reg 8 # current_temperature [7:0] $end
$var reg 2 $ mode [1:0] $end
$var reg 8 % target_temperature [7:0] $end
$scope module uut $end
$var wire 8 & current_temperature [7:0] $end
$var wire 2 ' mode [1:0] $end
$var wire 8 ( target_temperature [7:0] $end
$var reg 8 ) abs_diff_temperature [7:0] $end
$var reg 2 * air_condition [1:0] $end
$var reg 8 + diff_temperature [7:0] $end
$var reg 2 , heater [1:0] $end
$upscope $end
$upscope $end
$enddefinitions $end
$comment Show the parameter values. $end
$dumpall
$end
#0
$dumpvars
b0 ,
b101 +
b0 *
bx )
b10100 (
b0 '
b11001 &
b10100 %
b0 $
b11001 #
b0 "
b0 !
$end
#100000
b10 !
b10 ,
b11111011 +
b1111 #
b1111 &
b1 $
b1 '
#200000
b1 !
b1 ,
b11111100 +
b10000 #
b10000 &
#300000
b0 +
b10100 #
b10100 &
#400000
b101 +
b11001 #
b11001 &
#500000
b10 "
b10 *
b0 !
b0 ,
b10 $
b10 '
#600000
b1 "
b1 *
b100 +
b11000 #
b11000 &
#700000
b0 +
b10100 #
b10100 &
#800000
b11111011 +
b1111 #
b1111 &
#900000
b0 "
b0 *
b0 )
b0 +
b10100 #
b10100 &
b11 $
b11 '
#1000000
b1 "
b1 *
b1 )
b1 +
b10101 #
b10101 &
#1100000
b100 )
b100 +
b11000 #
b11000 &
#1200000
b10 "
b10 *
b101 )
b101 +
b11001 #
b11001 &
#1300000
b1 !
b1 ,
b0 "
b0 *
b1 )
b11111111 +
b10011 #
b10011 &
#1400000
b100 )
b11111100 +
b10000 #
b10000 &
#1500000
b10 !
b10 ,
b101 )
b11111011 +
b1111 #
b1111 &
#1600000
b11110110 %
b11110110 (
b11110001 #
b11110001 &
#1700000
b10 "
b10 *
b0 !
b0 ,
b101 +
b11111011 #
b11111011 &
