lab/source/Lab2_Task1.v
module Lab2_Task1 (
    input [2:0] in,
    output [1:0] out
  );

  wire [1:0] d_xor;
  wire [1:0] d_and;
  wire d_or;

  assign d_xor[0] = in[0] ^ in[1];
  assign d_xor[1] = d_xor[0] ^ in[2];
  assign d_and[0] = d_xor[0] & in[2];
  assign d_and[1] = in[0] & in[1];
  assign d_or = d_and[0] | d_and[1];

  assign out[0] = d_xor[1];
  assign out[1] = d_or;

endmodule

lab/source/tb_Lab2_Task1.v
`timescale 1ns/1ps

module tb_Lab2_Task1 (
  );

  reg [2:0] i;
  wire [1:0] o;

  Lab2_Task1 uut (
               .in(i),
               .out(o)
             );

  initial begin
    // initialize inputs
    // #100;
    i = 3'b000;
    // wait 100ns
    #100;
    // update inputs
    i = 3'b001;
    #100;
    // update inputs
    i = 3'b010;
    #100;
    // update inputs
    i = 3'b011;
    #100;
    // update inputs
    i = 3'b100;
    #100;
    // update inputs
    i = 3'b101;
    #100;
    // update inputs
    i = 3'b110;
    #100;
    // update inputs
    i = 3'b111;
    #100;
    $finish;
  end

  // output wave file
  initial begin
    $dumpfile("tb_Lab2_Task1.vcd");
    $dumpvars;
  end

endmodule

tb_Lab2_Task1.vcd
$date
	Mon Sep 21 11:28:02 2026
$end
$version
	Icarus Verilog
$end
$timescale
	1ps
$end
$scope module tb_Lab2_Task1 $end
$var wire 2 ! o [1:0] $end
$var reg 3 " i [2:0] $end
$scope module uut $end
$var wire 1 # d_or $end
$var wire 3 $ in [2:0] $end
$var wire 2 % out [1:0] $end
$var wire 2 & d_xor [1:0] $end
$var wire 2 ' d_and [1:0] $end
$upscope $end
$upscope $end
$enddefinitions $end
$comment Show the parameter values. $end
$dumpall
$end
#0
$dumpvars
b0 '
b0 &
b0 %
b0 $
0#
b0 "
b0 !
$end
#100000
b1 !
b1 %
b11 &
b1 "
b1 $
#200000
b10 "
b10 $
#300000
b10 !
b10 %
1#
b0 &
b10 '
b11 "
b11 $
#400000
b1 !
b1 %
0#
b10 &
b0 '
b100 "
b100 $
#500000
b10 !
b10 %
1#
b1 '
b1 &
b101 "
b101 $
#600000
b110 "
b110 $
#700000
b11 !
b11 %
b10 &
b10 '
b111 "
b111 $
